coca_websocket/__init__.py
coca_websocket/websocket.py
coca_websocket-0.1.8.dist-info/LICENSE
coca_websocket-0.1.8.dist-info/METADATA
coca_websocket-0.1.8.dist-info/WHEEL
coca_websocket-0.1.8.dist-info/RECORD
