Metadata-Version: 2.1
Name: coca-websocket
Version: 0.1.8
Summary: 
Home-page: https://github.com/CocaButon60s/coca_websocket
License: MIT
Author: Hiroyuki Ikuno
Author-email: sam2kaikaramegusuri@gmail.com
Requires-Python: >=3.11,<4.0
Classifier: License :: OSI Approved :: MIT License
Classifier: Programming Language :: Python :: 3
Classifier: Programming Language :: Python :: 3.11
Requires-Dist: websockets (>=11.0.3,<12.0.0)
